database/__init__.py
database/connection_manager.py
database/executor.py
database/schema_loader.py
database/adapters/__init__.py
database/adapters/base.py
database/adapters/clickhouse.py
database/adapters/mysql.py
database/adapters/postgresql.py
database/adapters/sqlite.py
llm/__init__.py
llm/llm_client.py
llm/prompt_builder.py
llm/schema_encoder.py
llm/sql_generator.py
mcp_server/__init__.py
mcp_server/handlers.py
mcp_server/server.py
mcp_sql_tool-0.1.0.dist-info/licenses/LICENSE
scripts/__init__.py
scripts/test_db_connection.py
security/__init__.py
security/audit_logger.py
security/permission_manager.py
security/query_limiter.py
security/sql_validator.py
storage/__init__.py
storage/db_manager.py
storage/query_history.py
storage/result_cache.py
storage/schema_cache.py
utils/__init__.py
utils/config_loader.py
utils/formatter.py
utils/logger.py
mcp_sql_tool-0.1.0.dist-info/METADATA
mcp_sql_tool-0.1.0.dist-info/WHEEL
mcp_sql_tool-0.1.0.dist-info/entry_points.txt
mcp_sql_tool-0.1.0.dist-info/top_level.txt
mcp_sql_tool-0.1.0.dist-info/RECORD
