Metadata-Version: 2.4
Name: mcp-sql-tool
Version: 0.1.0
Summary: 基于 MCP 协议的智能 SQL BI 工具，通过大模型自动生成 SQL 语句并执行数据库查询
Home-page: https://github.com/yourusername/mcp-sql-tool
Author: MCP SQL Tool Team
Author-email: 
License: MIT
Keywords: mcp,sql,llm,database,bi,nlp,natural-language
Classifier: Development Status :: 4 - Beta
Classifier: Intended Audience :: Developers
Classifier: Programming Language :: Python :: 3
Classifier: Programming Language :: Python :: 3.8
Classifier: Programming Language :: Python :: 3.9
Classifier: Programming Language :: Python :: 3.10
Classifier: Programming Language :: Python :: 3.11
Classifier: Programming Language :: Python :: 3.12
Classifier: Topic :: Database
Classifier: Topic :: Software Development :: Libraries :: Python Modules
Requires-Python: >=3.8
License-File: LICENSE
Requires-Dist: fastmcp>=0.9.0
Requires-Dist: pymysql>=1.1.0
Requires-Dist: psycopg2-binary>=2.9.9
Requires-Dist: clickhouse-driver>=0.2.6
Requires-Dist: openai>=1.0.0
Requires-Dist: anthropic>=0.18.0
Requires-Dist: dashscope>=1.17.0
Requires-Dist: pyyaml>=6.0
Requires-Dist: python-dotenv>=1.0.0
Requires-Dist: uvicorn>=0.24.0
Requires-Dist: sqlparse>=0.4.4
Provides-Extra: dev
Requires-Dist: pytest>=7.4.0; extra == "dev"
Requires-Dist: pytest-cov>=4.1.0; extra == "dev"
Requires-Dist: black>=23.0.0; extra == "dev"
Requires-Dist: flake8>=6.0.0; extra == "dev"
Requires-Dist: mypy>=1.0.0; extra == "dev"
Dynamic: home-page
Dynamic: license-file
Dynamic: requires-python
